mermaid_doc/__init__.py
mermaid_doc/server.py
mermaid_doc/docs/README.md
mermaid_doc/docs/syntax/architecture.md
mermaid_doc/docs/syntax/block.md
mermaid_doc/docs/syntax/c4.md
mermaid_doc/docs/syntax/classDiagram.md
mermaid_doc/docs/syntax/entityRelationshipDiagram.md
mermaid_doc/docs/syntax/examples.md
mermaid_doc/docs/syntax/flowchart.md
mermaid_doc/docs/syntax/gantt.md
mermaid_doc/docs/syntax/gitgraph.md
mermaid_doc/docs/syntax/kanban.md
mermaid_doc/docs/syntax/mindmap.md
mermaid_doc/docs/syntax/packet.md
mermaid_doc/docs/syntax/pie.md
mermaid_doc/docs/syntax/quadrantChart.md
mermaid_doc/docs/syntax/radar.md
mermaid_doc/docs/syntax/requirementDiagram.md
mermaid_doc/docs/syntax/sankey.md
mermaid_doc/docs/syntax/sequenceDiagram.md
mermaid_doc/docs/syntax/stateDiagram.md
mermaid_doc/docs/syntax/timeline.md
mermaid_doc/docs/syntax/userJourney.md
mermaid_doc/docs/syntax/xyChart.md
mermaid_doc/docs/syntax/zenuml.md
mermaid_doc/docs/syntax/img/Gantt-excluded-days-within.png
mermaid_doc/docs/syntax/img/Gantt-long-weekend-look.png
mermaid_doc/docs/syntax/img/zenuml-participant-annotators.png
mermaid_doc_mcp_server-0.2.0.dist-info/METADATA
mermaid_doc_mcp_server-0.2.0.dist-info/WHEEL
mermaid_doc_mcp_server-0.2.0.dist-info/entry_points.txt
mermaid_doc_mcp_server-0.2.0.dist-info/RECORD
