Metadata-Version: 2.4
Name: mermaid-doc-mcp-server
Version: 0.2.0
Summary: A Model Context Protocol (MCP) server that provides access to Mermaid diagram documentation.
Requires-Python: >=3.10
Requires-Dist: mcp>=1.6.0
